npasync/__init__.py
npasync/core/__init__.py
npasync/core/tools.py
npasync-2022.7.2.dist-info/LICENSE
npasync-2022.7.2.dist-info/METADATA
npasync-2022.7.2.dist-info/WHEEL
npasync-2022.7.2.dist-info/top_level.txt
npasync-2022.7.2.dist-info/RECORD
